[
  {
    "title": "خرید شارژ ایرانسل",
    "tracking_code": "9356286345632",
    "price": "250,000",
    "time": "22:40",
    "date": "1403/12/06",
    "status": true,
    "id": 1
  },
  {
    "title": "بلیت هواپیما",
    "tracking_code": "265432876539",
    "price": "460,000",
    "time": "18:17",
    "date": "1402/08/18",
    "status": false,
    "id": 2
  },
  {
    "title": "خرید شارژ ایرانسل",
    "tracking_code": "9356286345632",
    "price": "250,000",
    "time": "22:40",
    "date": "1403/12/06",
    "status": true,
    "id": 3
  },
  {
    "title": "بلیت هواپیما",
    "tracking_code": "265432876539",
    "price": "460,000",
    "time": "18:17",
    "date": "1402/08/18",
    "status": true,
    "id": 4
  },
  {
    "title": "خرید شارژ ایرانسل",
    "tracking_code": "9356286345632",
    "price": "250,000",
    "time": "22:40",
    "date": "1403/12/06",
    "status": true,
    "id": 5
  },
  {
    "title": "بلیت هواپیما",
    "tracking_code": "265432876539",
    "price": "460,000",
    "time": "18:17",
    "date": "1402/08/18",
    "status": true,
    "id": 6
  },
  {
    "title": "خرید شارژ ایرانسل",
    "tracking_code": "9356286345632",
    "price": "250,000",
    "time": "22:40",
    "date": "1403/12/06",
    "status": false,
    "id": 7
  },
  {
    "title": "بلیت هواپیما",
    "tracking_code": "265432876539",
    "price": "460,000",
    "time": "18:17",
    "date": "1402/08/18",
    "status": true,
    "id": 8
  },
  {
    "title": "خرید شارژ ایرانسل",
    "tracking_code": "9356286345632",
    "price": "250,000",
    "time": "22:40",
    "date": "1403/12/06",
    "status": true,
    "id": 9
  },
  {
    "title": "بلیت هواپیما",
    "tracking_code": "265432876539",
    "price": "460,000",
    "time": "18:17",
    "date": "1402/08/18",
    "status": true,
    "id": 10
  },
  {
    "title": "خرید شارژ ایرانسل",
    "tracking_code": "9356286345632",
    "price": "250,000",
    "time": "22:40",
    "date": "1403/12/06",
    "status": true,
    "id": 11
  },
  {
    "title": "بلیت هواپیما",
    "tracking_code": "265432876539",
    "price": "460,000",
    "time": "18:17",
    "date": "1402/08/18",
    "status": true,
    "id": 12
  },
  {
    "title": "خرید شارژ ایرانسل",
    "tracking_code": "9356286345632",
    "price": "250,000",
    "time": "22:40",
    "date": "1403/12/06",
    "status": true,
    "id": 13
  },
  {
    "title": "بلیت هواپیما",
    "tracking_code": "265432876539",
    "price": "460,000",
    "time": "18:17",
    "date": "1402/08/18",
    "status": true,
    "id": 14
  },
  {
    "title": "بلیت هواپیما",
    "tracking_code": "265432876539",
    "price": "460,000",
    "time": "18:17",
    "date": "1402/08/18",
    "status": true,
    "id": 15
  }
]
